chloros_sdk/__init__.py
chloros_sdk/__version__.py
chloros_sdk/exceptions.py
chloros_sdk/local.py
chloros_sdk-1.0.41.dist-info/licenses/LICENSE
chloros_sdk-1.0.41.dist-info/METADATA
chloros_sdk-1.0.41.dist-info/WHEEL
chloros_sdk-1.0.41.dist-info/top_level.txt
chloros_sdk-1.0.41.dist-info/RECORD
