Metadata-Version: 2.4
Name: chloros-sdk
Version: 1.0.41
Summary: Official Python SDK for MAPIR Chloros image processing
Home-page: https://www.mapir.camera
Author: MAPIR Inc.
Author-email: "MAPIR Inc." <info@mapir.camera>
License-Expression: LicenseRef-Proprietary
Project-URL: Homepage, https://www.mapir.camera
Project-URL: Documentation, https://docs.chloros.com
Project-URL: Source, https://github.com/mapircamera/chloros-sdk
Project-URL: Support, https://www.mapir.camera/community/contact
Keywords: chloros,mapir,multispectral,ndvi,image-processing,agriculture,remote-sensing
Platform: Windows
Platform: Linux
Classifier: Development Status :: 5 - Production/Stable
Classifier: Intended Audience :: Developers
Classifier: Intended Audience :: Science/Research
Classifier: Topic :: Scientific/Engineering :: Image Processing
Classifier: Operating System :: Microsoft :: Windows
Classifier: Operating System :: POSIX :: Linux
Classifier: Programming Language :: Python :: 3
Requires-Python: >=3.7
License-File: LICENSE
Requires-Dist: requests>=2.25.0
Provides-Extra: progress
Requires-Dist: sseclient-py>=1.7.2; extra == "progress"
Provides-Extra: dev
Requires-Dist: pytest>=6.0; extra == "dev"
Requires-Dist: pytest-cov>=2.10; extra == "dev"
Requires-Dist: black>=20.8b1; extra == "dev"
Requires-Dist: mypy>=0.800; extra == "dev"
Dynamic: author
Dynamic: home-page
Dynamic: license-file
Dynamic: platform
Dynamic: requires-python
